adder1.v
`timescale 1ns / 1ns
module adder1(
  input wire a,
  input wire b,
  input wire cin,
  output wire out,
  output wire cout
);
reg d;
reg q;
always @(a or b or cin)
begin
    q <= #3 (a&b)|(b&cin)|(a&cin);
    d <= #6 a^b^cin;
end
assign out = d;
assign cout = q;
endmodule

adder_posl.v
module adder_posl(
  input wire [3:0]a,
  input wire [3:0]b,
  output wire [3:0]out,
  output wire carry
);
wire [3:0]car;
adder1 ad0(.a(a[0]), .b(b[0]), .cin(1'h0), .out(out[0]), .cout(car[1]));
adder1 ad1(.a(a[1]), .b(b[1]), .cin(car[1]), .out(out[1]), .cout(car[2]));
adder1 ad2(.a(a[2]), .b(b[2]), .cin(car[2]), .out(out[2]), .cout(car[3]));
adder1 ad3(.a(a[3]), .b(b[3]), .cin(car[3]), .out(out[3]), .cout(carry));
endmodule

adder_par.v
module adder_par(
  input wire [3:0]a,
  input wire [3:0]b,
  output wire [3:0]out,
  output wire carry
);
reg [3:0]g;
reg [3:0]p;
reg [3:0]carr;
reg carryr;
wire [3:0]car;

always @(a or b)
begin
  g <= a&b;
  p <= a|b;
  carr[0] <= 0;
  #1;
  carr[1] <= g[0];
  #1;
  carr[2] <= g[1]|(p[1]&g[0]);
  #1;
  carr[3] <= g[2]|(p[2]&g[1])|(p[2]&p[1]&g[0]);
  #2;
  carryr <= g[3]|(p[3]&g[2])|(p[3]&p[2]&g[1])|(p[3]&p[2]&p[1]&g[0]);
end
assign car = carr;
assign carry = carryr;

adder1 ad0(.a(a[0]), .b(b[0]), .cin(car[0]), .out(out[0]));
adder1 ad1(.a(a[1]), .b(b[1]), .cin(car[1]), .out(out[1]));
adder1 ad2(.a(a[2]), .b(b[2]), .cin(car[2]), .out(out[2]));
adder1 ad3(.a(a[3]), .b(b[3]), .cin(car[3]), .out(out[3]));
endmodule

adder_tb.v
`timescale 1ns / 1ns

module testbench;

reg [3:0]var_a;
reg [3:0]var_b;
wire [3:0]r_out_par;
wire [3:0]r_out_posl;
wire r_carry_par;
wire r_carry_posl;

//instance of module being studied
adder_par adder_pari(
  .a(var_a),
  .b(var_b),
  .out(r_out_par),
  .carry(r_carry_par)
);
adder_posl adder_posli(
  .a(var_a),
  .b(var_b),
  .out(r_out_posl),
  .carry(r_carry_posl)
);

initial
begin
  $dumpfile("out.vcd");
  $dumpvars(0,testbench);
	
  var_a = 4'h5;
  var_b = 4'h0;
   #30;
  var_a = 4'h1;
  var_b = 4'hA;
   #30;
  var_a = 4'h5;
  var_b = 4'hA;
   #30;
  var_a = 4'h9;
  var_b = 4'h4;
   #30;
  var_a = 4'h9;
  var_b = 4'h9;
   #30;
  var_a = 4'h9;
  var_b = 4'h6;
   #30;
  $finish;
end



endmodule

out.vcd
$date
	Sun May 15 18:16:25 2022
$end
$version
	Icarus Verilog
$end
$timescale
	1ns
$end
$scope module testbench $end
$var wire 4 ! r_out_posl [3:0] $end
$var wire 4 " r_out_par [3:0] $end
$var wire 1 # r_carry_posl $end
$var wire 1 $ r_carry_par $end
$var reg 4 % var_a [3:0] $end
$var reg 4 & var_b [3:0] $end
$scope module adder_pari $end
$var wire 4 ' a [3:0] $end
$var wire 4 ( b [3:0] $end
$var wire 1 $ carry $end
$var wire 4 ) out [3:0] $end
$var wire 4 * car [3:0] $end
$var reg 4 + carr [3:0] $end
$var reg 1 , carryr $end
$var reg 4 - g [3:0] $end
$var reg 4 . p [3:0] $end
$scope module ad0 $end
$var wire 1 / a $end
$var wire 1 0 b $end
$var wire 1 1 cin $end
$var wire 1 2 cout $end
$var wire 1 3 out $end
$var reg 1 3 d $end
$var reg 1 4 q $end
$upscope $end
$scope module ad1 $end
$var wire 1 5 a $end
$var wire 1 6 b $end
$var wire 1 7 cin $end
$var wire 1 8 cout $end
$var wire 1 9 out $end
$var reg 1 9 d $end
$var reg 1 : q $end
$upscope $end
$scope module ad2 $end
$var wire 1 ; a $end
$var wire 1 < b $end
$var wire 1 = cin $end
$var wire 1 > cout $end
$var wire 1 ? out $end
$var reg 1 ? d $end
$var reg 1 @ q $end
$upscope $end
$scope module ad3 $end
$var wire 1 A a $end
$var wire 1 B b $end
$var wire 1 C cin $end
$var wire 1 D cout $end
$var wire 1 E out $end
$var reg 1 E d $end
$var reg 1 F q $end
$upscope $end
$upscope $end
$scope module adder_posli $end
$var wire 4 G a [3:0] $end
$var wire 4 H b [3:0] $end
$var wire 4 I out [3:0] $end
$var wire 1 # carry $end
$var wire 4 J car [3:0] $end
$scope module ad0 $end
$var wire 1 K a $end
$var wire 1 L b $end
$var wire 1 M cin $end
$var wire 1 N out $end
$var wire 1 O cout $end
$var reg 1 N d $end
$var reg 1 O q $end
$upscope $end
$scope module ad1 $end
$var wire 1 P a $end
$var wire 1 Q b $end
$var wire 1 R cin $end
$var wire 1 S out $end
$var wire 1 T cout $end
$var reg 1 S d $end
$var reg 1 T q $end
$upscope $end
$scope module ad2 $end
$var wire 1 U a $end
$var wire 1 V b $end
$var wire 1 W cin $end
$var wire 1 X out $end
$var wire 1 Y cout $end
$var reg 1 X d $end
$var reg 1 Y q $end
$upscope $end
$scope module ad3 $end
$var wire 1 Z a $end
$var wire 1 [ b $end
$var wire 1 \ cin $end
$var wire 1 # cout $end
$var wire 1 ] out $end
$var reg 1 ] d $end
$var reg 1 ^ q $end
$upscope $end
$upscope $end
$upscope $end
$enddefinitions $end
#0
$dumpvars
x^
x]
x\
0[
0Z
xY
xX
xW
0V
1U
xT
xS
xR
0Q
0P
xO
xN
0M
0L
1K
bxz J
bx I
b0 H
b101 G
xF
xE
xD
xC
0B
0A
x@
x?
x>
x=
0<
1;
x:
x9
x8
x7
06
05
x4
x3
x2
01
00
1/
b101 .
b0 -
x,
bx0 +
bx0 *
bx )
b0 (
b101 '
b0 &
b101 %
x$
x#
bx "
bx !
$end
#1
07
bx00 *
bx00 +
#2
0=
bx000 *
bx000 +
#3
0C
0R
0W
b0 *
b0 +
02
04
08
0:
0D
0F
0O
bx00z J
0T
0#
0^
#5
0$
0,
0>
0@
#6
0\
b0z J
0Y
bx1 "
bx1 )
13
bx1 !
bx1 I
1N
#7
bx01 "
bx01 )
09
#8
bx101 "
bx101 )
1?
#9
b101 "
b101 )
0E
0S
bx101 !
bx101 I
1X
#12
b101 !
b101 I
0]
#30
b1011 .
16
1B
1Q
1[
0;
0U
b1010 &
b1010 (
b1010 H
b1 %
b1 '
b1 G
#36
19
1E
1S
1]
b1011 "
b1011 )
0?
b1011 !
b1011 I
0X
#60
b1111 .
1;
1U
b101 %
b101 '
b101 G
#66
b1111 "
b1111 )
1?
b1111 !
b1111 I
1X
#90
b1101 .
06
1<
0B
0Q
1V
0[
0;
1A
0U
1Z
b100 &
b100 (
b100 H
b1001 %
b1001 '
b1001 G
#96
b1101 "
b1101 )
09
b1101 !
b1101 I
0S
#120
b1001 .
b1001 -
10
0<
1B
1L
0V
1[
b1001 &
b1001 (
b1001 H
#121
17
b10 *
b10 +
#123
1R
12
14
1D
1F
b1z J
1O
1#
1^
#125
1$
1,
#126
03
0?
b0 "
b0 )
0E
0N
0X
b0 !
b0 I
0]
#127
b10 "
b10 )
19
#129
b10 !
b10 I
1S
#150
b1111 .
b0 -
00
16
1<
0B
0L
1Q
1V
0[
b110 &
b110 (
b110 H
#151
07
b0 *
b0 +
#153
0R
1W
02
04
18
1:
0D
0F
0O
b10z J
1T
0#
0^
#154
08
0:
#155
0$
0,
#156
0W
1\
0T
b100z J
1Y
13
09
1?
b1101 "
b1101 )
1E
1N
0S
1X
b1101 !
b1101 I
1]
#157
b1111 "
b1111 )
19
#159
0\
b0z J
0Y
1#
1^
1S
b1011 !
b1011 I
0X
#162
0#
0^
1X
b111 !
b111 I
0]
#165
b1111 !
b1111 I
1]
